aceui/__init__.py
aceui/base/__init__.py
aceui/base/basepage.py
aceui/cli.py
aceui/config/config.yaml
aceui/lib/__init__.py
aceui/lib/config.py
aceui/lib/core.py
aceui/lib/emailstmp.py
aceui/lib/excel.py
aceui/lib/gl.py
aceui/lib/HTMLTESTRunnerCN.py
aceui/scaffold/__init__.py
aceui/scaffold/data/activityCreate64.yaml
aceui/scaffold/debug.py
aceui/scaffold/pages/__init__.py
aceui/scaffold/pages/activityCreate64Page.py
aceui/scaffold/readme.txt
aceui/scaffold/testCase/__init__.py
aceui/scaffold/testCase/testActivityCreate64.py
aceui-1.0.21.dist-info/entry_points.txt
aceui-1.0.21.dist-info/WHEEL
aceui-1.0.21.dist-info/METADATA
aceui-1.0.21.dist-info/RECORD
