Metadata-Version: 2.1
Name: aceui
Version: 1.0.21
Summary: 基于Selenium的UI自动化测试框架
Home-page: https://github.com/HttpTesting/aceui
License: Apache-2.0
Keywords: selenium,po,HTMLTestRunner,test
Author: 天枢
Author-email: lengyaohui@163.com
Classifier: Development Status :: 3 - Alpha
Classifier: Environment :: Console
Classifier: License :: OSI Approved :: Apache Software License
Classifier: Operating System :: Microsoft :: Windows
Classifier: Programming Language :: Python :: 2
Classifier: Programming Language :: Python :: 2.7
Classifier: Programming Language :: Python :: 3
Classifier: Programming Language :: Python :: 3.4
Classifier: Programming Language :: Python :: 3.5
Classifier: Programming Language :: Python :: 3.6
Classifier: Programming Language :: Python :: 3.7
Classifier: Programming Language :: Python :: 3.8
Classifier: Programming Language :: Python :: 3.9
Classifier: Topic :: Software Development :: Documentation
Classifier: Topic :: Software Development :: Libraries :: Python Modules
Requires-Dist: Pillow (==5.3.0)
Requires-Dist: PyAutoIt (==0.6.0)
Requires-Dist: PyYAML (==5.1.1)
Requires-Dist: ddt (==1.1.3)
Requires-Dist: requests (==2.25.0)
Requires-Dist: selenium (==3.141.0)
Requires-Dist: xlrd (==1.2.0)
Requires-Dist: xlutils (==2.0.0)
Requires-Dist: xlwt (==1.3.0)
Project-URL: Repository, https://github.com/HttpTesting/aceui
